ernie/__init__.py
ernie/aggregation_strategies.py
ernie/ernie.py
ernie/helper.py
ernie/models.py
ernie/split_strategies.py
test/__init__.py
test/dump_load.py
test/load_csv.py
test/load_model.py
test/predict.py
test/split_aggregate.py
ernie-1.2405.2.dist-info/LICENSE
ernie-1.2405.2.dist-info/METADATA
ernie-1.2405.2.dist-info/WHEEL
ernie-1.2405.2.dist-info/top_level.txt
ernie-1.2405.2.dist-info/RECORD
